{"dungeonlist":
	[
		{
			"dungeon_name": "Wind Range Camp",
			"dungeon_type": "campsite",
			"location": "east area",
			"date_found": "August 8, 2011",
			"populated": "yes",
			"friendly": "no",
			"occupant": "human",
			"category": "bandits",
			"loot_rating": "2",
			"no_loot_here": "no",
			"notes": "Found some leather greaves."
		},
		{
			"dungeon_name": "Sercen Camp",
			"dungeon_type": "campsite",
			"location": "east area",
			"date_found": "August 9, 2011",
			"populated": "yes",
			"friendly": "yes",
			"occupant": "human",
			"category": "trainer",
			"loot_rating": "0",
			"no_loot_here": "yes",
			"notes": "Alchemy trainer."
		},
		{
			"dungeon_name": "Carbo's Camp",
			"dungeon_type": "campsite",
			"location": "south area",
			"date_found": "August 10, 2011",
			"populated": "yes",
			"friendly": "no",
			"occupant": "human",
			"category": "bandits",
			"loot_rating": "3",
			"no_loot_here": "no",
			"notes": "Bandits have lockpicks and gold on them."
		},
		{
			"dungeon_name": "Bawnwatch Camp",
			"dungeon_type": "campsite",
			"location": "east area",
			"date_found": "August 7, 2011",
			"populated": "no",
			"friendly": "no",
			"occupant": "none",
			"category": "none",
			"loot_rating": "0",
			"no_loot_here": "yes",
			"notes": "You can watch the ghost of the Forlorn Watchman. Good camp to drop loot."
		},
		{
			"dungeon_name": "Black Dog Camp",
			"dungeon_type": "campsite",
			"location": "southwest area",
			"date_found": "August 11, 2011",
			"populated": "yes",
			"friendly": "no",
			"occupant": "human",
			"category": "bandits",
			"loot_rating": "0",
			"no_loot_here": "yes",
			"notes": "One drunk bandit here."
		}
	]
}